{
  "Abyssal Ward": "offhand",
  "Accursed Amulet of the Apprentice": "amulet",
  "Aegis": "offhand",
  "Aetherwing": "offhand",
  "Aidan's Scar": "weapon",
  "Akarat's Devotion": "weapon",
  "Aldur's Advance": "boots",
  "Aldur's Deception": "armor",
  "Aldur's Stony Gaze": "helm",
  "Aldur's Watchtower": "helm",
  "Alma Negra": "offhand",
  "Amazon": "weapon",
  "Amber Gnarled Staff of Teleportation": "weapon",
  "Amulet": "amulet",
  "Ancient's Foresight": "offhand",
  "Ancient's Scripture": "offhand",
  "Ancients' Pledge": "offhand",
  "Andariel's Visage": "helm",
  "Angelic Halo": "ring",
  "Angelic Mantle": "ring",
  "Angelic Raiment": "ring",
  "Angelic Wings": "amulet",
  "Anvilguard Strap": "offhand",
  "Arachnid Mesh": "belt",
  "Arcanna's Deathwand": "weapon",
  "Arcanna's Flesh": "armor",
  "Arcanna's Head": "helm",
  "Arcanna's Sign": "amulet",
  "Arcanna's Tricks": "helm",
  "Archer's Demonhide Gloves of Wealth": "gloves",
  "Archer's Gauntlets of Alacrity": "gloves",
  "Archon Plate": "armor",
  "Archon Staff": "weapon",
  "Arctic Binding": "belt",
  "Arctic Furs": "armor",
  "Arctic Gear": "armor",
  "Arctic Horn": "weapon",
  "Arctic Mitts": "gloves",
  "Arioc's Needle": "weapon",
  "Arkaine's Valor": "armor",
  "Arm of King Leoric": "weapon",
  "Armageddon's Blade": "weapon",
  "Armet": "helm",
  "Arreat's Face": "helm",
  "Assassin": "weapon",
  "Assault Helmet": "helm",
  "Astreon's Iron Ward": "weapon",
  "Asylum": "weapon",
  "Athena's Wrath": "weapon",
  "Athlete's Gauntlets of the Apprentice": "gloves",
  "Athlete's Light Gauntlets of Alacrity": "gloves",
  "Athlete's Light Gauntlets of the Apprentice": "gloves",
  "Athlete's Sharp Arrows of the Bat": "offhand",
  "Athlete's War Gauntlets of the Apprentice": "gloves",
  "Atlantean": "weapon",
  "Atma's Scarab": "amulet",
  "Atma's Wail": "armor",
  "Avenger Guard": "helm",
  "Axe of Fechmar": "weapon",
  "Azurewrath": "weapon",
  "Baezil's Vortex": "weapon",
  "Balefire": "offhand",
  "Balrog Spear": "weapon",
  "Band of Skulls": "belt",
  "Bane Ash": "weapon",
  "Bannerlord's Call": "offhand",
  "Baranar's Star": "weapon",
  "Barbed Club": "weapon",
  "Barbed Shield": "offhand",
  "Bartuc's Cut-Throat": "weapon",
  "Basilisk's Quill": "offhand",
  "Battle Belt": "belt",
  "Battle Boots": "boots",
  "Battlebranch": "weapon",
  "Beast": "weapon",
  "Berserker's Arsenal": "helm",
  "Berserker's Hatchet": "weapon",
  "Berserker's Hauberk": "armor",
  "Berserker's Headgear": "helm",
  "Biggin's Bonnet": "helm",
  "Bing Sz Wang": "weapon",
  "Black Hades": "armor",
  "Blackbog's Sharp": "weapon",
  "Blackhand Key": "weapon",
  "Blackhorn's Face": "helm",
  "Blackleach Blade": "weapon",
  "Blackoak Shield": "offhand",
  "Blacktongue": "weapon",
  "Blade Talons": "weapon",
  "Blade of Ali Baba": "weapon",
  "Bladebone": "weapon",
  "Bladebuckle": "belt",
  "Blastbark": "weapon",
  "Blinkbat's Form": "armor",
  "Blood Crescent": "weapon",
  "Blood Raven's Charge": "weapon",
  "Bloodfist": "gloves",
  "Bloodletter": "weapon",
  "Bloodmoon": "weapon",
  "Bloodrise": "weapon",
  "Bloodthief": "weapon",
  "Bloodtree Stump": "weapon",
  "Bone": "armor",
  "Bone Wand": "weapon",
  "Boneflame": "offhand",
  "Boneflesh": "armor",
  "Bonehew": "weapon",
  "Boneshade": "weapon",
  "Boneslayer Blade": "weapon",
  "Bonesnap": "weapon",
  "Boneweave": "armor",
  "Boneweave Boots": "boots",
  "Bows 2": "weapon",
  "Brainhew": "weapon",
  "Bramble": "armor",
  "Bramble Mitts": "gloves",
  "Brand": "weapon",
  "Breath of the Dying": "weapon",
  "Brimstone Rain": "weapon",
  "Bul-Kathos' Children": "ring",
  "Bul-Kathos' Death Band": "ring",
  "Bul-Kathos' Sacred Charge": "weapon",
  "Bul-Kathos' Tribal Guardian": "weapon",
  "Bul-Kathos' Wedding Band": "ring",
  "Buriza-Do Kyanon": "weapon",
  "Butcher's Pupil": "weapon",
  "Bverrit Keep": "offhand",
  "Cage of the Unsullied": "armor",
  "Call to Arms": "weapon",
  "Carin Shard": "weapon",
  "Carnage Helm": "helm",
  "Carrion Wind": "ring",
  "Cat's Eye": "amulet",
  "Cathan's Mesh": "armor",
  "Cathan's Rule": "weapon",
  "Cathan's Seal": "ring",
  "Cathan's Sigil": "amulet",
  "Cathan's Traps": "helm",
  "Cathan's Visage": "helm",
  "Centurion": "armor",
  "Cerebus' Bite": "helm",
  "Chain Boots": "boots",
  "Chain Mail": "armor",
  "Chains of Honor": "armor",
  "Champion Axe": "weapon",
  "Chance Guards": "gloves",
  "Chaos": "weapon",
  "Chaos Armor": "armor",
  "Chieftain": "weapon",
  "Chromatic Ire": "weapon",
  "Circlet": "helm",
  "Civerb's Cudgel": "weapon",
  "Civerb's Icon": "amulet",
  "Civerb's Vestments": "offhand",
  "Civerb's Ward": "offhand",
  "Cleglaw's Brace": "gloves",
  "Cleglaw's Claw": "offhand",
  "Cleglaw's Pincers": "gloves",
  "Cleglaw's Tooth": "weapon",
  "Cliffkiller": "weapon",
  "Cloudcrack": "weapon",
  "Coif of Glory": "helm",
  "Coldkill": "weapon",
  "Coldsteel Eye": "weapon",
  "Colossus Blade": "weapon",
  "Colossus Crossbow": "weapon",
  "Colossus Girdle": "belt",
  "Colossus Voulge": "weapon",
  "Communal Amulet of Life Everlasting": "amulet",
  "Conqueror Crown": "helm",
  "Constricting Loop": "ring",
  "Coronet": "helm",
  "Corpsemourn": "armor",
  "Cow King's Hide": "armor",
  "Cow King's Hooves": "boots",
  "Cow King's Horns": "helm",
  "Cow King's Leathers": "helm",
  "Crackleshot": "weapon",
  "Crainte Vomir": "weapon",
  "Cranebeak": "weapon",
  "Cranium Basher": "weapon",
  "Credendum": "belt",
  "Crescent Moon": "weapon",
  "Crow Caw": "armor",
  "Crown Shield": "offhand",
  "Crown of Ages": "helm",
  "Crown of Thieves": "helm",
  "Crushflange": "weapon",
  "Crystal Sword": "weapon",
  "Cuirass": "armor",
  "Culwen's Point": "weapon",
  "Cunning Amulet of Excellence": "amulet",
  "Cunning Amulet of Luck": "amulet",
  "Cunning Amulet of Might": "amulet",
  "Cunning Amulet of Remedy": "amulet",
  "Cunning Scissors Katar of Hypothermia": "weapon",
  "Cyclopean Roar": "helm",
  "Dangoon's Teaching": "weapon",
  "Dark Abyss": "armor",
  "Dark Adherent": "armor",
  "Dark Clan Crusher": "weapon",
  "Darkforce Spawn": "offhand",
  "Darkglow": "armor",
  "Darksight Helm": "helm",
  "Death": "weapon",
  "Death Cleaver": "weapon",
  "Death's Disguise": "belt",
  "Death's Fathom": "weapon",
  "Death's Guard": "belt",
  "Death's Hand": "gloves",
  "Death's Touch": "weapon",
  "Death's Web": "weapon",
  "Deathspade": "weapon",
  "Defender": "offhand",
  "Delirium": "helm",
  "Demon Limb": "weapon",
  "Demon Machine": "weapon",
  "Demon's Arch": "weapon",
  "Demonhide Boots": "boots",
  "Demonhide Gloves": "gloves",
  "Demonhide Sash": "belt",
  "Demonhorn's Edge": "helm",
  "Denmother": "helm",
  "Destroyer Helm": "helm",
  "Destruction": "weapon",
  "Diadem": "helm",
  "Diamond Mail": "armor",
  "Diggler": "weapon",
  "Dimoak's Hew": "weapon",
  "Disciple": "armor",
  "Djinn Slayer": "weapon",
  "Dominion": "weapon",
  "Doom": "weapon",
  "Doom's Finger": "offhand",
  "Doombringer": "weapon",
  "Doomslinger": "weapon",
  "Dracul's Grasp": "gloves",
  "Dragon": "armor",
  "Dragon 2": "offhand",
  "Dragon Chang": "weapon",
  "Dragonscale": "offhand",
  "Dream": "helm",
  "Dream 2": "offhand",
  "Duress": "armor",
  "Duriel's Shell": "armor",
  "Duskdeep": "helm",
  "Dwarf Star": "ring",
  "Eaglehorn": "weapon",
  "Earth Shifter": "weapon",
  "Earth Spirit": "helm",
  "Earthshaker": "weapon",
  "Ebonbane": "weapon",
  "Echo": "offhand",
  "Echo 2": "weapon",
  "Echoing Amulet of Atlus": "amulet",
  "Echoing Amulet of Sorcery": "amulet",
  "Echoing Amulet of the Apprentice": "amulet",
  "Echoing Balanced Axe of Crushing": "weapon",
  "Echoing Balanced Axe of Ease": "weapon",
  "Echoing Balanced Axe of Havoc": "weapon",
  "Echoing Balanced Axe of Slaughter": "weapon",
  "Echoing Balanced Axe of the Bear": "weapon",
  "Echoing Balanced Axe of the Vampire": "weapon",
  "Echoing Bastard Sword of Quickness": "weapon",
  "Echoing Glaive of Alacrity": "weapon",
  "Echoing Glaive of Anthrax": "weapon",
  "Echoing Glaive of Carnage": "weapon",
  "Echoing Glaive of Desolation": "weapon",
  "Echoing Glaive of Ease": "weapon",
  "Echoing Glaive of Hematic": "weapon",
  "Echoing Glaive of Maelstrom": "weapon",
  "Echoing Glaive of Performance": "weapon",
  "Echoing Glaive of Quickness": "weapon",
  "Echoing Glaive of Readiness": "weapon",
  "Echoing Glaive of Simplicity": "weapon",
  "Echoing Glaive of Swiftness": "weapon",
  "Echoing Glaive of Transcendence": "weapon",
  "Echoing Glaive of the Lamprey": "weapon",
  "Echoing Glaive of the Leech": "weapon",
  "Echoing Glaive of the Locust": "weapon",
  "Echoing Sabre of the Vampire": "weapon",
  "Echoing Throwing Spear of Alacrity": "weapon",
  "Echoing Throwing Spear of Carnage": "weapon",
  "Echoing Throwing Spear of Damage Amplification": "weapon",
  "Echoing Throwing Spear of Destruction": "weapon",
  "Echoing Throwing Spear of Ease": "weapon",
  "Echoing Throwing Spear of Evisceration": "weapon",
  "Echoing Throwing Spear of Gore": "weapon",
  "Echoing Throwing Spear of Gory": "weapon",
  "Echoing Throwing Spear of Havoc": "weapon",
  "Echoing Throwing Spear of Might": "weapon",
  "Echoing Throwing Spear of Performance": "weapon",
  "Echoing Throwing Spear of Pulverizing": "weapon",
  "Echoing Throwing Spear of Readiness": "weapon",
  "Echoing Throwing Spear of Swiftness": "weapon",
  "Echoing Throwing Spear of Transcendence": "weapon",
  "Echoing Throwing Spear of Winter": "weapon",
  "Echoing Throwing Spear of the Bear": "weapon",
  "Echoing Throwing Spear of the Giant": "weapon",
  "Echoing Throwing Spear of the Glacier": "weapon",
  "Echoing Throwing Spear of the Lamprey": "weapon",
  "Echoing Throwing Spear of the Leech": "weapon",
  "Echoing Throwing Spear of the Locust": "weapon",
  "Echoing Throwing Spear of the Ox": "weapon",
  "Echoing Throwing Spear of the Vampire": "weapon",
  "Echoing Throwing Spear of the Wraith": "weapon",
  "Echoing War Javelin of Ice Barrage": "weapon",
  "Echoing War Sword of Carnage": "weapon",
  "Echoing War Sword of Might": "weapon",
  "Edge": "weapon",
  "Embersworn": "weapon",
  "Embossed Plate": "armor",
  "Endlesshail": "weapon",
  "Enigma": "armor",
  "Enlightenment": "armor",
  "Ephemeral": "offhand",
  "Epiphany": "offhand",
  "Eschuta's Temper": "weapon",
  "Eternity": "weapon",
  "Ethereal Edge": "weapon",
  "Executioner's Justice": "weapon",
  "Exile": "offhand",
  "Eye of Etlich": "amulet",
  "Face of Horror": "helm",
  "Faith": "weapon",
  "Famine": "weapon",
  "Fanged Helm": "helm",
  "Felloak": "weapon",
  "Fenris": "helm",
  "Ferocity": "helm",
  "Fetid Sprinkler": "weapon",
  "Firelizard's Talons": "weapon",
  "Flamebellow": "weapon",
  "Fleshrender": "weapon",
  "Fleshripper": "weapon",
  "Flickering Flame": "helm",
  "Flying Axe": "weapon",
  "Fortitude": "armor",
  "Fortitude 2": "weapon",
  "Frostburn": "gloves",
  "Frostwind": "weapon",
  "Frozen Sorrow": "offhand",
  "Furious Amulet of the Vampire": "amulet",
  "Fury": "weapon",
  "Fury Visor": "helm",
  "Gauntlets": "gloves",
  "Gavel of Pain": "weapon",
  "General's Tan Do Li Ga": "weapon",
  "Gerke's Sanctuary": "offhand",
  "Ghost Glaive": "weapon",
  "Ghostflame": "weapon",
  "Ghoulhide": "gloves",
  "Giant Maimer": "weapon",
  "Giant Skull": "helm",
  "Gimmershred": "weapon",
  "Ginther's Rift": "weapon",
  "Glacial Amulet of Chance": "amulet",
  "Glacial Amulet of the Squid": "amulet",
  "Gladiator's Bane": "armor",
  "Gleamscythe": "weapon",
  "Gloom": "armor",
  "Gloom's Trap": "belt",
  "Gnasher": "weapon",
  "Goblin Toe": "boots",
  "Goldskin": "armor",
  "Goldstrike Arch": "weapon",
  "Goldwrap": "belt",
  "Golemlord's Amulet of Life": "amulet",
  "Golemlord's Amulet of Performance": "amulet",
  "Golemlord's Amulet of the Apprentice": "amulet",
  "Golemlord's Amulet of the Ox": "amulet",
  "Golemlord's Bone Wand of the Eldritch": "weapon",
  "Golemlord's Tomb Wand of Brilliance": "weapon",
  "Gore Rider": "boots",
  "Gorefoot": "boots",
  "Goreshovel": "weapon",
  "Gothic Shield": "offhand",
  "Grandfather": "weapon",
  "Gravenspine": "weapon",
  "Gravepalm": "gloves",
  "Great Hauberk": "armor",
  "Greater Talons": "weapon",
  "Greaves": "boots",
  "Greyform": "armor",
  "Grief": "weapon",
  "Griffon's Eye": "helm",
  "Grim Reaper": "weapon",
  "Grim Shield": "offhand",
  "Grim's Burning Dead": "weapon",
  "Griswold's Edge": "weapon",
  "Griswold's Heart": "armor",
  "Griswold's Honor": "offhand",
  "Griswold's Redemption": "weapon",
  "Guardian Angel": "armor",
  "Guardian Naga": "weapon",
  "Guillaume's Face": "helm",
  "Gull": "weapon",
  "Gut Siphon": "weapon",
  "Hadriel's Hand": "weapon",
  "Haemosu's Adamant": "offhand",
  "Halaberd's Reign": "helm",
  "Hand of Blessed Light": "weapon",
  "Hand of Broc": "gloves",
  "Hand of Justice": "weapon",
  "Harlequin Crest": "helm",
  "Harmony": "weapon",
  "Hawkmail": "armor",
  "Head Hunter's Glory": "offhand",
  "Headstriker": "weapon",
  "Heart Carver": "weapon",
  "Heart of the Oak": "weapon",
  "Heaven's Brethren": "helm",
  "Heaven's Light": "weapon",
  "Heavenly Garb": "armor",
  "Heavy Bolts": "offhand",
  "Heavy Boots": "boots",
  "Heavy Bracers": "gloves",
  "Hellcast": "weapon",
  "Hellclap": "weapon",
  "Hellmouth": "gloves",
  "Hellplague": "weapon",
  "Hellrack": "weapon",
  "Hellslayer": "weapon",
  "Herald of Zakarum": "offhand",
  "Hexfire": "weapon",
  "Hierophant's Amulet of Fortune": "amulet",
  "Highlord's Wrath": "amulet",
  "Holy Thunder": "weapon",
  "Homunculus": "offhand",
  "Hone Sundan": "weapon",
  "Honor": "weapon",
  "Horizon's Tornado": "weapon",
  "Horned Helm": "helm",
  "Hotspur": "boots",
  "Howltusk": "helm",
  "Hsarus' Defense": "boots",
  "Hsarus' Iron Fist": "offhand",
  "Hsarus' Iron Heel": "boots",
  "Hsarus' Iron Stay": "belt",
  "Humongous": "weapon",
  "Husoldal Evo": "weapon",
  "Hustle": "armor",
  "Hwanin's Blessing": "belt",
  "Hwanin's Justice": "weapon",
  "Hwanin's Majesty": "helm",
  "Hwanin's Splendor": "helm",
  "Hydra Bow": "weapon",
  "Ice": "weapon",
  "Iceblink": "armor",
  "Ichorsting": "weapon",
  "Immortal King's Detail": "belt",
  "Immortal King's Forge": "gloves",
  "Immortal King's Pillar": "boots",
  "Immortal King's Soul Cage": "armor",
  "Immortal King's Stone Crusher": "weapon",
  "Immortal King's Will": "helm",
  "Impaler": "weapon",
  "Infernal Cranium": "helm",
  "Infernal Sign": "belt",
  "Infernal Spire (Infernal Torch)": "weapon",
  "Infernal Tools": "helm",
  "Infernostride": "boots",
  "Infinity": "weapon",
  "Innocence": "armor",
  "Insight": "weapon",
  "Iratha's Coil": "helm",
  "Iratha's Collar": "amulet",
  "Iratha's Cord": "belt",
  "Iratha's Cuff": "gloves",
  "Iratha's Finery": "helm",
  "Iron Jang Bong": "weapon",
  "Iron Pelt": "armor",
  "Ironstone": "weapon",
  "Isenhart's Armory": "helm",
  "Isenhart's Case": "armor",
  "Isenhart's Horns": "helm",
  "Isenhart's Lightbrand": "weapon",
  "Isenhart's Parry": "offhand",
  "Islestrike": "weapon",
  "Itherael's Path": "boots",
  "Jade Talon": "weapon",
  "Jade Tan Do": "weapon",
  "Jalal's Mane": "helm",
  "Javelins": "weapon",
  "Jawbone Visor": "helm",
  "Kadala's Heirloom": "ring",
  "Kalan's Legacy": "offhand",
  "Keeper's Amulet of Enlightenment": "amulet",
  "Keeper's Amulet of Life Everlasting": "amulet",
  "Keeper's Amulet of Wealth": "amulet",
  "Keeper's Amulet of the Apprentice": "amulet",
  "Keeper's Amulet of the Giant": "amulet",
  "Keeper's Amulet of the Mind": "amulet",
  "Keeper's Amulet of the Squid": "amulet",
  "Kelpie Snare": "weapon",
  "Kenshi's Amulet of Defiance": "amulet",
  "Kenshi's Gauntlets of Alacrity": "gloves",
  "Kenshi's Gauntlets of the Leech": "gloves",
  "Kenshi's Light Gauntlets of Alacrity": "gloves",
  "Kenshi's War Gauntlets of Alacrity": "gloves",
  "Khalim's Will": "weapon",
  "Kinemil's Awl": "weapon",
  "King's Grace": "weapon",
  "Kingslayer": "weapon",
  "Kira's Guardian": "helm",
  "Knell Striker": "weapon",
  "Kraken Shell": "armor",
  "Kuko Shakaku": "weapon",
  "Lacerator": "weapon",
  "Lacquered Plate": "armor",
  "Lance Guard": "offhand",
  "Lance of Yaggai": "weapon",
  "Lancer's Amulet of Clarity": "amulet",
  "Lancer's Bramble Mitts of Alacrity": "gloves",
  "Lancer's Gauntlets of Alacrity": "gloves",
  "Langer Briser": "weapon",
  "Last Wish": "weapon",
  "Lava Gout": "gloves",
  "Lawbringer": "weapon",
  "Laying of Hands": "gloves",
  "Leadcrow": "weapon",
  "Legendary Mallet": "weapon",
  "Lenymo": "belt",
  "Leoric's Mithril Bane": "weapon",
  "Leviathan": "armor",
  "Lich Wand": "weapon",
  "Lidless Wall": "offhand",
  "Light Gauntlets": "gloves",
  "Light Plated Boots": "boots",
  "Lightsabre": "weapon",
  "Lion Helm": "helm",
  "Lionheart": "armor",
  "Lore": "helm",
  "Loricated Mail": "armor",
  "M'avina's Battle Hymn": "helm",
  "M'avina's Caster": "weapon",
  "M'avina's Embrace": "armor",
  "M'avina's Icy Clutch": "gloves",
  "M'avina's Tenet": "belt",
  "M'avina's True Sight": "helm",
  "Maelstrom": "weapon",
  "Mage Plate": "armor",
  "Mage Slayer": "weapon",
  "Magefist": "gloves",
  "Magewrath": "weapon",
  "Magnus' Skin": "gloves",
  "Mahim-Oak Curio": "amulet",
  "Malice": "weapon",
  "Manald Heal": "ring",
  "Mang Song's Lesson": "weapon",
  "Mara's Kaleidoscope": "amulet",
  "Marrowwalk": "boots",
  "Martyrdom": "offhand",
  "Matriarchal Bow": "weapon",
  "Matriarchal Javelin": "weapon",
  "Meat Scraper": "weapon",
  "Mechanist's Gnarled Staff of Teleportation": "weapon",
  "Medusa's Gaze": "offhand",
  "Melody": "weapon",
  "Memory": "weapon",
  "Merman's Sprocket": "boots",
  "Mesh Belt": "belt",
  "Messerschmidt's Reaver": "weapon",
  "Metalgrid": "amulet",
  "Milabrega's Diadem": "helm",
  "Milabrega's Orb": "offhand",
  "Milabrega's Regalia": "helm",
  "Milabrega's Robe": "armor",
  "Milabrega's Rod": "weapon",
  "Minotaur": "weapon",
  "Mirrored Boots": "boots",
  "Mist": "weapon",
  "Mithril Coil": "belt",
  "Monarch": "offhand",
  "Moonfall": "weapon",
  "Moser's Blessed Circle": "offhand",
  "Myth": "armor",
  "Nadir": "helm",
  "Nagelring": "ring",
  "Naj's Ancient Vestige": "helm",
  "Naj's Circlet": "helm",
  "Naj's Light Plate": "armor",
  "Naj's Puzzler": "weapon",
  "Natalya's Mark": "weapon",
  "Natalya's Odium": "helm",
  "Natalya's Shadow": "armor",
  "Natalya's Soul": "boots",
  "Natalya's Totem": "helm",
  "Nature's Peace": "ring",
  "Necromancer's Bone Wand of Ashes": "weapon",
  "Neophyte": "weapon",
  "Nethercrux": "weapon",
  "Nightsmoke": "belt",
  "Nightwing's Veil": "helm",
  "Nokozan Relic": "amulet",
  "Nord's Tenderizer": "weapon",
  "Nosferatu's Coil": "belt",
  "Oath": "weapon",
  "Obedience": "weapon",
  "Obsession": "weapon",
  "Occultist": "gloves",
  "Odium": "weapon",
  "Ogre Gauntlets": "gloves",
  "Ogre Maul": "weapon",
  "Ondal's Almighty": "helm",
  "Ondal's Wisdom": "weapon",
  "Ormus' Robes": "armor",
  "Ornate Plate": "armor",
  "Orphan's Call": "helm",
  "Overlord's Helm": "helm",
  "Paladin": "weapon",
  "Passion": "weapon",
  "Patriarch": "weapon",
  "Pattern": "weapon",
  "Peace": "armor",
  "Peasant Crown": "helm",
  "Pelta Lunata": "offhand",
  "Petrified Wand": "weapon",
  "Phoenix": "offhand",
  "Phoenix 2": "weapon",
  "Pierre Tombale Couant": "weapon",
  "Plague": "weapon",
  "Plague Bearer": "weapon",
  "Plated Belt": "belt",
  "Pluckeye": "weapon",
  "Pompeii's Wrath": "weapon",
  "Powered Amulet of the Apprentice": "amulet",
  "Pride": "weapon",
  "Principle": "armor",
  "Prudence": "armor",
  "Purgatory": "armor",
  "Purity": "weapon",
  "Pus Spitter": "weapon",
  "Que-Hegan's Wisdom": "armor",
  "Quetzalcoatl": "helm",
  "Radament's Sphere": "offhand",
  "Radiance": "helm",
  "Raekor's Virtue": "helm",
  "Rage Mask": "helm",
  "Rain": "armor",
  "Rakescar": "weapon",
  "Ramfodder": "offhand",
  "Rampage": "weapon",
  "Rapture": "weapon",
  "Rattlecage": "armor",
  "Raven Claw": "weapon",
  "Raven Frost": "ring",
  "Ravenlore": "helm",
  "Razor Arrows": "offhand",
  "Razor's Edge": "weapon",
  "Razorswitch": "weapon",
  "Razortail": "belt",
  "Razortine": "weapon",
  "Reaper's Toll": "weapon",
  "Redeemer": "weapon",
  "Reinforced Mace": "weapon",
  "Reinforcing Fetish Trophy of Wizardry": "offhand",
  "Rhyme": "offhand",
  "Ribcracker": "weapon",
  "Rift": "weapon",
  "Ring": "ring",
  "Riphook": "weapon",
  "Ripsaw": "weapon",
  "Rising Sun": "amulet",
  "Rite of Passage": "boots",
  "Rixot's Keen": "weapon",
  "Rockfleece": "armor",
  "Rockstopper": "helm",
  "Rogue's Bow": "weapon",
  "Rose Branded Amulet of Warmth": "amulet",
  "Rose Branded Amulet of the Apprentice": "amulet",
  "Rune Master": "weapon",
  "Rusthandle": "weapon",
  "Sacred Totem": "offhand",
  "Sage's Defiance": "helm",
  "Salamander": "weapon",
  "Sanctuary": "offhand",
  "Sander's Folly": "helm",
  "Sander's Paragon": "helm",
  "Sander's Riprap": "boots",
  "Sander's Superstition": "weapon",
  "Sander's Taboo": "gloves",
  "Sandstorm Trek": "boots",
  "Sankekur's Fall": "offhand",
  "Saracen's Chance": "amulet",
  "Savage Helmet": "helm",
  "Sazabi's Cobalt Redeemer": "weapon",
  "Sazabi's Ghost Liberator": "armor",
  "Sazabi's Grand Tribute": "helm",
  "Sazabi's Mental Sheath": "helm",
  "Scale Mail": "armor",
  "Scarab Husk": "armor",
  "Scarabshell Boots": "boots",
  "Schaefer's Hammer": "weapon",
  "Scintillating Ring of Chance": "ring",
  "Scissors Quhab": "weapon",
  "Seraph's Hymn": "amulet",
  "Serpent Lord": "weapon",
  "Sexton Trophy": "offhand",
  "Shadow Amulet of Might": "amulet",
  "Shadow Amulet of the Apprentice": "amulet",
  "Shadow Amulet of the Squid": "amulet",
  "Shadow Dancer": "boots",
  "Shadow Killer": "gloves",
  "Shadow Plate": "armor",
  "Shadow Scissors Katar of the Wraith": "weapon",
  "Shadowfang": "weapon",
  "Shaftstop": "armor",
  "Sharkskin Belt": "belt",
  "Sharkskin Boots": "boots",
  "Sharkskin Gloves": "gloves",
  "Sharktooth Armor": "armor",
  "Sharp Arrows": "offhand",
  "Shatterblade": "weapon",
  "Shatterhead": "offhand",
  "Siggard's Staunch": "belt",
  "Sigon's Complete Steel": "helm",
  "Sigon's Gage": "gloves",
  "Sigon's Guard": "offhand",
  "Sigon's Sabot": "boots",
  "Sigon's Shelter": "armor",
  "Sigon's Visor": "helm",
  "Sigon's Wrap": "belt",
  "Silence": "weapon",
  "Silks of the Victor": "armor",
  "Silkweave": "boots",
  "Skewer of Krintiz": "weapon",
  "Skin of the Flayed One": "armor",
  "Skin of the Vipermagi": "armor",
  "Skull Collector": "weapon",
  "Skull Splitter": "weapon",
  "Skullder's Ire": "armor",
  "Skyfall": "weapon",
  "Skystrike": "weapon",
  "Skywarden": "offhand",
  "Smoke": "armor",
  "Snakecord": "belt",
  "Snowclash": "belt",
  "Sorceress": "weapon",
  "Soul Drainer": "gloves",
  "Soul Harvest": "weapon",
  "Soulfeast Tine": "weapon",
  "Soulflay": "weapon",
  "Sparking Mail": "armor",
  "Spears 2": "weapon",
  "Spectral Shard": "weapon",
  "Spellsteel": "weapon",
  "Spiderweb Sash": "belt",
  "Spike Thorn": "offhand",
  "Spineripper": "weapon",
  "Spire of Honor": "weapon",
  "Spire of Lazarus": "weapon",
  "Spired Helm": "helm",
  "Spirit": "offhand",
  "Spirit 2": "weapon",
  "Spirit Forge": "armor",
  "Spirit Keeper": "helm",
  "Spirit Shroud": "armor",
  "Spirit Ward": "offhand",
  "Splendor": "offhand",
  "Stag Bow": "weapon",
  "Stalker's Cull": "weapon",
  "Stealskull": "helm",
  "Stealth": "armor",
  "Steel": "weapon",
  "Steel Carapace": "armor",
  "Steel Pillar": "weapon",
  "Steel Shade": "helm",
  "Steelclash": "offhand",
  "Steeldriver": "weapon",
  "Steelgoad": "weapon",
  "Steelrend": "gloves",
  "Stone": "armor",
  "Stone Crusher": "weapon",
  "Stone of Jordan": "ring",
  "Stoneraven": "weapon",
  "Stormchaser": "offhand",
  "Stormeye": "weapon",
  "Stormguild": "offhand",
  "Stormlash": "weapon",
  "Stormrider": "weapon",
  "Stormshield": "offhand",
  "Stormspike": "weapon",
  "Stormspire": "weapon",
  "Stormstrike": "weapon",
  "Stoutnail": "weapon",
  "Strength": "weapon",
  "String of Ears": "belt",
  "Stygian Pilum": "weapon",
  "Suicide Branch": "weapon",
  "Sureshrill Frost": "weapon",
  "Swiftwind Needle": "offhand",
  "Swordback Hold": "offhand",
  "Swordguard": "weapon",
  "Taebaek's Glory": "offhand",
  "Tal Rasha's Adjudication": "amulet",
  "Tal Rasha's Fine-Spun Cloth": "belt",
  "Tal Rasha's Guardianship": "armor",
  "Tal Rasha's Horadric Crest": "helm",
  "Tal Rasha's Lidless Eye": "weapon",
  "Tal Rasha's Wrappings": "helm",
  "Tancred's Battlegear": "helm",
  "Tancred's Hobnails": "boots",
  "Tancred's Skull": "helm",
  "Tancred's Spine": "armor",
  "Tancred's Weird": "amulet",
  "Tannr Gorerod": "weapon",
  "Tarnhelm": "helm",
  "Tearhaunch": "boots",
  "Telling of Beads": "amulet",
  "Tempest": "weapon",
  "Templar's Might": "armor",
  "The Abyssal Ward": "offhand",
  "The Aetherwing": "offhand",
  "The Aidan's Scar": "weapon",
  "The Akarat's Devotion": "weapon",
  "The Aldur's Advance": "boots",
  "The Aldur's Deception": "armor",
  "The Aldur's Stony Gaze": "helm",
  "The Aldur's Watchtower": "helm",
  "The Alma Negra": "offhand",
  "The Amazon": "weapon",
  "The Ancient's Foresight": "offhand",
  "The Ancient's Scripture": "offhand",
  "The Ancients' Pledge": "offhand",
  "The Andariel's Visage": "helm",
  "The Angelic Halo": "ring",
  "The Angelic Mantle": "ring",
  "The Angelic Raiment": "ring",
  "The Angelic Wings": "amulet",
  "The Anvilguard Strap": "offhand",
  "The Arachnid Mesh": "belt",
  "The Arcanna's Deathwand": "weapon",
  "The Arcanna's Flesh": "armor",
  "The Arcanna's Head": "helm",
  "The Arcanna's Sign": "amulet",
  "The Arcanna's Tricks": "helm",
  "The Arctic Binding": "belt",
  "The Arctic Furs": "armor",
  "The Arctic Gear": "armor",
  "The Arctic Horn": "weapon",
  "The Arctic Mitts": "gloves",
  "The Arioc's Needle": "weapon",
  "The Arkaine's Valor": "armor",
  "The Arm of King Leoric": "weapon",
  "The Armageddon's Blade": "weapon",
  "The Arreat's Face": "helm",
  "The Assassin": "weapon",
  "The Astreon's Iron Ward": "weapon",
  "The Asylum": "weapon",
  "The Athena's Wrath": "weapon",
  "The Atlantean": "weapon",
  "The Atma's Scarab": "amulet",
  "The Atma's Wail": "armor",
  "The Axe of Fechmar": "weapon",
  "The Azurewrath": "weapon",
  "The Baezil's Vortex": "weapon",
  "The Balefire": "offhand",
  "The Band of Skulls": "belt",
  "The Bane Ash": "weapon",
  "The Bannerlord's Call": "offhand",
  "The Baranar's Star": "weapon",
  "The Bartuc's Cut-Throat": "weapon",
  "The Basilisk's Quill": "offhand",
  "The Battlebranch": "weapon",
  "The Beast": "weapon",
  "The Berserker's Arsenal": "helm",
  "The Berserker's Hatchet": "weapon",
  "The Berserker's Hauberk": "armor",
  "The Berserker's Headgear": "helm",
  "The Biggin's Bonnet": "helm",
  "The Bing Sz Wang": "weapon",
  "The Black Hades": "armor",
  "The Blackbog's Sharp": "weapon",
  "The Blackhand Key": "weapon",
  "The Blackhorn's Face": "helm",
  "The Blackleach Blade": "weapon",
  "The Blackoak Shield": "offhand",
  "The Blacktongue": "weapon",
  "The Blade of Ali Baba": "weapon",
  "The Bladebone": "weapon",
  "The Bladebuckle": "belt",
  "The Blastbark": "weapon",
  "The Blinkbat's Form": "armor",
  "The Blood Crescent": "weapon",
  "The Bloodfist": "gloves",
  "The Bloodletter": "weapon",
  "The Bloodmoon": "weapon",
  "The Bloodrise": "weapon",
  "The Bloodthief": "weapon",
  "The Bloodtree Stump": "weapon",
  "The Bone": "armor",
  "The Boneflame": "offhand",
  "The Boneflesh": "armor",
  "The Bonehew": "weapon",
  "The Boneshade": "weapon",
  "The Boneslayer Blade": "weapon",
  "The Bonesnap": "weapon",
  "The Bows 2": "weapon",
  "The Brainhew": "weapon",
  "The Bramble": "armor",
  "The Brand": "weapon",
  "The Breath of the Dying": "weapon",
  "The Brimstone Rain": "weapon",
  "The Bul-Kathos' Children": "ring",
  "The Bul-Kathos' Death Band": "ring",
  "The Bul-Kathos' Sacred Charge": "weapon",
  "The Bul-Kathos' Tribal Guardian": "weapon",
  "The Bul-Kathos' Wedding Band": "ring",
  "The Buriza-Do Kyanon": "weapon",
  "The Butcher's Pupil": "weapon",
  "The Bverrit Keep": "offhand",
  "The Cage of the Unsullied": "armor",
  "The Call to Arms": "weapon",
  "The Carin Shard": "weapon",
  "The Carrion Wind": "ring",
  "The Cat's Eye": "amulet",
  "The Cathan's Mesh": "armor",
  "The Cathan's Rule": "weapon",
  "The Cathan's Seal": "ring",
  "The Cathan's Sigil": "amulet",
  "The Cathan's Traps": "helm",
  "The Cathan's Visage": "helm",
  "The Centurion": "armor",
  "The Cerebus' Bite": "helm",
  "The Chains of Honor": "armor",
  "The Chance Guards": "gloves",
  "The Chaos": "weapon",
  "The Chieftain": "weapon",
  "The Chromatic Ire": "weapon",
  "The Civerb's Cudgel": "weapon",
  "The Civerb's Icon": "amulet",
  "The Civerb's Vestments": "offhand",
  "The Civerb's Ward": "offhand",
  "The Cleglaw's Brace": "gloves",
  "The Cleglaw's Claw": "offhand",
  "The Cleglaw's Pincers": "gloves",
  "The Cleglaw's Tooth": "weapon",
  "The Cliffkiller": "weapon",
  "The Cloudcrack": "weapon",
  "The Coif of Glory": "helm",
  "The Coldkill": "weapon",
  "The Coldsteel Eye": "weapon",
  "The Constricting Loop": "ring",
  "The Corpsemourn": "armor",
  "The Cow King's Hide": "armor",
  "The Cow King's Hooves": "boots",
  "The Cow King's Horns": "helm",
  "The Cow King's Leathers": "helm",
  "The Crackleshot": "weapon",
  "The Crainte Vomir": "weapon",
  "The Cranebeak": "weapon",
  "The Cranium Basher": "weapon",
  "The Credendum": "belt",
  "The Crescent Moon": "amulet",
  "The Crow Caw": "armor",
  "The Crown of Ages": "helm",
  "The Crown of Thieves": "helm",
  "The Crushflange": "weapon",
  "The Culwen's Point": "weapon",
  "The Cyclopean Roar": "helm",
  "The Dangoon's Teaching": "weapon",
  "The Dark Abyss": "armor",
  "The Dark Adherent": "armor",
  "The Dark Clan Crusher": "weapon",
  "The Darkforce Spawn": "offhand",
  "The Darkglow": "armor",
  "The Darksight Helm": "helm",
  "The Death": "weapon",
  "The Death Cleaver": "weapon",
  "The Death's Disguise": "belt",
  "The Death's Guard": "belt",
  "The Death's Hand": "gloves",
  "The Death's Touch": "weapon",
  "The Death's Web": "weapon",
  "The Deathspade": "weapon",
  "The Delirium": "helm",
  "The Demon Limb": "weapon",
  "The Demon Machine": "weapon",
  "The Demon's Arch": "weapon",
  "The Demonhorn's Edge": "helm",
  "The Denmother": "helm",
  "The Destruction": "weapon",
  "The Diggler": "weapon",
  "The Dimoak's Hew": "weapon",
  "The Disciple": "armor",
  "The Djinn Slayer": "weapon",
  "The Dominion": "weapon",
  "The Doom": "weapon",
  "The Doom's Finger": "offhand",
  "The Doombringer": "weapon",
  "The Doomslinger": "weapon",
  "The Dracul's Grasp": "gloves",
  "The Dragon": "armor",
  "The Dragon 2": "offhand",
  "The Dragon Chang": "weapon",
  "The Dragonscale": "offhand",
  "The Dream": "helm",
  "The Dream 2": "offhand",
  "The Duress": "armor",
  "The Duriel's Shell": "armor",
  "The Duskdeep": "helm",
  "The Dwarf Star": "ring",
  "The Eaglehorn": "weapon",
  "The Earth Shifter": "weapon",
  "The Earthshaker": "weapon",
  "The Echo": "offhand",
  "The Echo 2": "weapon",
  "The Edge": "weapon",
  "The Embersworn": "weapon",
  "The Endlesshail": "weapon",
  "The Enigma": "armor",
  "The Enlightenment": "armor",
  "The Ephemeral": "offhand",
  "The Epiphany": "offhand",
  "The Eschuta's Temper": "weapon",
  "The Eternity": "weapon",
  "The Ethereal Edge": "weapon",
  "The Executioner's Justice": "weapon",
  "The Exile": "offhand",
  "The Eye of Etlich": "amulet",
  "The Face of Horror": "helm",
  "The Faith": "weapon",
  "The Famine": "weapon",
  "The Felloak": "weapon",
  "The Fenris": "helm",
  "The Ferocity": "helm",
  "The Fetid Sprinkler": "weapon",
  "The Firelizard's Talons": "weapon",
  "The Flamebellow": "weapon",
  "The Fleshrender": "weapon",
  "The Fleshripper": "weapon",
  "The Flickering Flame": "helm",
  "The Fortitude": "armor",
  "The Fortitude 2": "weapon",
  "The Frostburn": "gloves",
  "The Frostwind": "weapon",
  "The Frozen Sorrow": "offhand",
  "The Fury": "weapon",
  "The Gavel of Pain": "weapon",
  "The General's Tan Do Li Ga": "weapon",
  "The Gerke's Sanctuary": "offhand",
  "The Ghostflame": "weapon",
  "The Ghoulhide": "gloves",
  "The Giant Maimer": "weapon",
  "The Giant Skull": "helm",
  "The Gimmershred": "weapon",
  "The Ginther's Rift": "weapon",
  "The Gladiator's Bane": "armor",
  "The Gleamscythe": "weapon",
  "The Gloom": "armor",
  "The Gloom's Trap": "belt",
  "The Gnasher": "weapon",
  "The Goblin Toe": "boots",
  "The Goldskin": "armor",
  "The Goldstrike Arch": "weapon",
  "The Goldwrap": "belt",
  "The Gore Rider": "boots",
  "The Gorefoot": "boots",
  "The Goreshovel": "weapon",
  "The Grandfather": "weapon",
  "The Gravenspine": "weapon",
  "The Gravepalm": "gloves",
  "The Greyform": "armor",
  "The Grief": "weapon",
  "The Griffon's Eye": "helm",
  "The Grim Reaper": "weapon",
  "The Grim's Burning Dead": "weapon",
  "The Griswold's Edge": "weapon",
  "The Griswold's Heart": "armor",
  "The Griswold's Honor": "offhand",
  "The Griswold's Redemption": "weapon",
  "The Guardian Angel": "armor",
  "The Guardian Naga": "weapon",
  "The Guillaume's Face": "helm",
  "The Gull": "weapon",
  "The Gut Siphon": "weapon",
  "The Hadriel's Hand": "weapon",
  "The Haemosu's Adamant": "armor",
  "The Halaberd's Reign": "helm",
  "The Hand of Blessed Light": "weapon",
  "The Hand of Broc": "gloves",
  "The Hand of Justice": "weapon",
  "The Harlequin Crest": "helm",
  "The Harmony": "weapon",
  "The Hawkmail": "armor",
  "The Head Hunter's Glory": "offhand",
  "The Headstriker": "weapon",
  "The Heart Carver": "weapon",
  "The Heart of the Oak": "weapon",
  "The Heaven's Brethren": "helm",
  "The Heaven's Light": "weapon",
  "The Heavenly Garb": "armor",
  "The Hellcast": "weapon",
  "The Hellclap": "weapon",
  "The Hellmouth": "gloves",
  "The Hellplague": "weapon",
  "The Hellrack": "weapon",
  "The Hellslayer": "weapon",
  "The Herald of Zakarum": "offhand",
  "The Hexfire": "weapon",
  "The Highlord's Wrath": "amulet",
  "The Holy Thunder": "weapon",
  "The Homunculus": "offhand",
  "The Hone Sundan": "weapon",
  "The Honor": "weapon",
  "The Horizon's Tornado": "weapon",
  "The Hotspur": "boots",
  "The Howltusk": "helm",
  "The Hsarus' Defense": "boots",
  "The Hsarus' Iron Fist": "offhand",
  "The Hsarus' Iron Heel": "boots",
  "The Hsarus' Iron Stay": "belt",
  "The Humongous": "weapon",
  "The Husoldal Evo": "weapon",
  "The Hustle": "armor",
  "The Hwanin's Blessing": "belt",
  "The Hwanin's Justice": "weapon",
  "The Hwanin's Majesty": "helm",
  "The Hwanin's Splendor": "helm",
  "The Ice": "weapon",
  "The Iceblink": "armor",
  "The Ichorsting": "weapon",
  "The Immortal King's Detail": "belt",
  "The Immortal King's Forge": "gloves",
  "The Immortal King's Pillar": "boots",
  "The Immortal King's Soul Cage": "armor",
  "The Immortal King's Stone Crusher": "weapon",
  "The Impaler": "weapon",
  "The Infernal Cranium": "helm",
  "The Infernal Sign": "belt",
  "The Infernal Spire (Infernal Torch)": "weapon",
  "The Infernal Tools": "helm",
  "The Infernostride": "boots",
  "The Infinity": "weapon",
  "The Innocence": "armor",
  "The Insight": "weapon",
  "The Iratha's Coil": "helm",
  "The Iratha's Collar": "amulet",
  "The Iratha's Cord": "belt",
  "The Iratha's Cuff": "gloves",
  "The Iratha's Finery": "helm",
  "The Iron Jang Bong": "weapon",
  "The Iron Pelt": "armor",
  "The Ironstone": "weapon",
  "The Isenhart's Armory": "helm",
  "The Isenhart's Case": "armor",
  "The Isenhart's Horns": "helm",
  "The Isenhart's Lightbrand": "weapon",
  "The Isenhart's Parry": "offhand",
  "The Islestrike": "weapon",
  "The Itherael's Path": "boots",
  "The Jade Talon": "weapon",
  "The Jade Tan Do": "weapon",
  "The Jalal's Mane": "helm",
  "The Kadala's Heirloom": "ring",
  "The Kalan's Legacy": "offhand",
  "The Kelpie Snare": "weapon",
  "The Kinemil's Awl": "weapon",
  "The King's Grace": "weapon",
  "The Kingslayer": "weapon",
  "The Kira's Guardian": "helm",
  "The Knell Striker": "weapon",
  "The Kuko Shakaku": "weapon",
  "The Lacerator": "weapon",
  "The Lance Guard": "offhand",
  "The Lance of Yaggai": "weapon",
  "The Langer Briser": "weapon",
  "The Last Wish": "weapon",
  "The Lava Gout": "gloves",
  "The Lawbringer": "weapon",
  "The Leadcrow": "weapon",
  "The Lenymo": "belt",
  "The Leoric's Mithril Bane": "weapon",
  "The Leviathan": "armor",
  "The Lidless Wall": "offhand",
  "The Lightsabre": "weapon",
  "The Lionheart": "armor",
  "The Lore": "helm",
  "The M'avina's Battle Hymn": "helm",
  "The M'avina's Caster": "weapon",
  "The M'avina's Embrace": "armor",
  "The M'avina's Icy Clutch": "gloves",
  "The M'avina's Tenet": "belt",
  "The M'avina's True Sight": "helm",
  "The Maelstrom": "weapon",
  "The Mage Slayer": "weapon",
  "The Magefist": "gloves",
  "The Magewrath": "weapon",
  "The Magnus' Skin": "gloves",
  "The Mahim-Oak Curio": "amulet",
  "The Malice": "weapon",
  "The Manald Heal": "ring",
  "The Mang Song's Lesson": "weapon",
  "The Mara's Kaleidoscope": "amulet",
  "The Marrowwalk": "boots",
  "The Martyrdom": "offhand",
  "The Meat Scraper": "weapon",
  "The Medusa's Gaze": "offhand",
  "The Melody": "weapon",
  "The Memory": "weapon",
  "The Merman's Sprocket": "boots",
  "The Messerschmidt's Reaver": "weapon",
  "The Metalgrid": "amulet",
  "The Milabrega's Diadem": "helm",
  "The Milabrega's Orb": "offhand",
  "The Milabrega's Regalia": "helm",
  "The Milabrega's Robe": "armor",
  "The Milabrega's Rod": "weapon",
  "The Minotaur": "weapon",
  "The Mist": "weapon",
  "The Moonfall": "weapon",
  "The Moser's Blessed Circle": "offhand",
  "The Myth": "armor",
  "The Nadir": "helm",
  "The Nagelring": "ring",
  "The Naj's Ancient Vestige": "helm",
  "The Naj's Circlet": "helm",
  "The Naj's Light Plate": "armor",
  "The Naj's Puzzler": "weapon",
  "The Natalya's Mark": "weapon",
  "The Natalya's Odium": "helm",
  "The Natalya's Shadow": "armor",
  "The Natalya's Soul": "boots",
  "The Natalya's Totem": "helm",
  "The Nature's Peace": "ring",
  "The Neophyte": "weapon",
  "The Nethercrux": "weapon",
  "The Nightsmoke": "belt",
  "The Nightwing's Veil": "helm",
  "The Nokozan Relic": "amulet",
  "The Nord's Tenderizer": "weapon",
  "The Nosferatu's Coil": "belt",
  "The Oath": "weapon",
  "The Obedience": "weapon",
  "The Obsession": "weapon",
  "The Occultist": "gloves",
  "The Oculus": "weapon",
  "The Odium": "weapon",
  "The Ondal's Almighty": "helm",
  "The Ondal's Wisdom": "weapon",
  "The Ormus' Robes": "armor",
  "The Orphan's Call": "helm",
  "The Overlord's Helm": "helm",
  "The Paladin": "weapon",
  "The Passion": "weapon",
  "The Patriarch": "weapon",
  "The Pattern": "weapon",
  "The Peace": "armor",
  "The Peasant Crown": "helm",
  "The Pelta Lunata": "offhand",
  "The Phoenix": "offhand",
  "The Phoenix 2": "weapon",
  "The Pierre Tombale Couant": "weapon",
  "The Plague": "weapon",
  "The Plague Bearer": "weapon",
  "The Pluckeye": "weapon",
  "The Pompeii's Wrath": "weapon",
  "The Pride": "weapon",
  "The Principle": "armor",
  "The Prudence": "armor",
  "The Purgatory": "armor",
  "The Purity": "weapon",
  "The Pus Spitter": "weapon",
  "The Que-Hegan's Wisdom": "armor",
  "The Quetzalcoatl": "helm",
  "The Radament's Sphere": "offhand",
  "The Radiance": "helm",
  "The Raekor's Virtue": "helm",
  "The Rain": "armor",
  "The Rakescar": "weapon",
  "The Ramfodder": "offhand",
  "The Rampage": "weapon",
  "The Rapture": "weapon",
  "The Rattlecage": "armor",
  "The Raven Claw": "weapon",
  "The Raven Frost": "ring",
  "The Ravenlore": "helm",
  "The Razor's Edge": "weapon",
  "The Razorswitch": "weapon",
  "The Razortail": "belt",
  "The Razortine": "weapon",
  "The Reaper's Toll": "weapon",
  "The Redeemer": "weapon",
  "The Rhyme": "offhand",
  "The Ribcracker": "weapon",
  "The Rift": "weapon",
  "The Riphook": "weapon",
  "The Ripsaw": "weapon",
  "The Rising Sun": "amulet",
  "The Rite of Passage": "boots",
  "The Rixot's Keen": "weapon",
  "The Rockfleece": "armor",
  "The Rockstopper": "helm",
  "The Rogue's Bow": "weapon",
  "The Rune Master": "weapon",
  "The Rusthandle": "weapon",
  "The Sacred Totem": "offhand",
  "The Sage's Defiance": "helm",
  "The Salamander": "weapon",
  "The Sanctuary": "offhand",
  "The Sander's Folly": "helm",
  "The Sander's Paragon": "helm",
  "The Sander's Riprap": "boots",
  "The Sander's Superstition": "weapon",
  "The Sander's Taboo": "gloves",
  "The Sandstorm Trek": "boots",
  "The Sankekur's Fall": "offhand",
  "The Saracen's Chance": "amulet",
  "The Sazabi's Cobalt Redeemer": "weapon",
  "The Sazabi's Ghost Liberator": "armor",
  "The Sazabi's Grand Tribute": "helm",
  "The Sazabi's Mental Sheath": "helm",
  "The Schaefer's Hammer": "weapon",
  "The Seraph's Hymn": "amulet",
  "The Serpent Lord": "weapon",
  "The Shadow Dancer": "boots",
  "The Shadow Killer": "gloves",
  "The Shadowfang": "weapon",
  "The Shaftstop": "armor",
  "The Shatterblade": "weapon",
  "The Shatterhead": "offhand",
  "The Siggard's Staunch": "belt",
  "The Sigon's Complete Steel": "helm",
  "The Sigon's Gage": "gloves",
  "The Sigon's Guard": "offhand",
  "The Sigon's Sabot": "boots",
  "The Sigon's Shelter": "armor",
  "The Sigon's Visor": "helm",
  "The Sigon's Wrap": "belt",
  "The Silence": "weapon",
  "The Silks of the Victor": "armor",
  "The Silkweave": "boots",
  "The Skewer of Krintiz": "weapon",
  "The Skin of the Flayed One": "armor",
  "The Skin of the Vipermagi": "armor",
  "The Skull Collector": "weapon",
  "The Skull Splitter": "weapon",
  "The Skullder's Ire": "armor",
  "The Skyfall": "weapon",
  "The Skystrike": "weapon",
  "The Skywarden": "offhand",
  "The Smoke": "armor",
  "The Snakecord": "belt",
  "The Snowclash": "belt",
  "The Sorceress": "weapon",
  "The Soul Drainer": "gloves",
  "The Soul Harvest": "weapon",
  "The Soulfeast Tine": "weapon",
  "The Soulflay": "weapon",
  "The Sparking Mail": "armor",
  "The Spears 2": "weapon",
  "The Spectral Shard": "weapon",
  "The Spellsteel": "weapon",
  "The Spike Thorn": "offhand",
  "The Spineripper": "weapon",
  "The Spire of Honor": "weapon",
  "The Spire of Lazarus": "weapon",
  "The Spirit": "offhand",
  "The Spirit 2": "weapon",
  "The Spirit Forge": "armor",
  "The Spirit Keeper": "helm",
  "The Spirit Shroud": "armor",
  "The Spirit Ward": "offhand",
  "The Splendor": "offhand",
  "The Stalker's Cull": "weapon",
  "The Stealskull": "helm",
  "The Stealth": "armor",
  "The Steel": "weapon",
  "The Steel Carapace": "armor",
  "The Steel Pillar": "weapon",
  "The Steel Shade": "helm",
  "The Steelclash": "offhand",
  "The Steeldriver": "weapon",
  "The Steelgoad": "weapon",
  "The Steelrend": "gloves",
  "The Stone": "armor",
  "The Stone Crusher": "weapon",
  "The Stone of Jordan": "ring",
  "The Stormchaser": "offhand",
  "The Stormeye": "weapon",
  "The Stormguild": "offhand",
  "The Stormlash": "weapon",
  "The Stormrider": "weapon",
  "The Stormshield": "offhand",
  "The Stormspike": "weapon",
  "The Stormspire": "weapon",
  "The Stormstrike": "weapon",
  "The Stoutnail": "weapon",
  "The Strength": "weapon",
  "The String of Ears": "belt",
  "The Suicide Branch": "weapon",
  "The Sureshrill Frost": "weapon",
  "The Swiftwind Needle": "offhand",
  "The Swordback Hold": "offhand",
  "The Swordguard": "weapon",
  "The Taebaek's Glory": "offhand",
  "The Tal Rasha's Adjudication": "amulet",
  "The Tal Rasha's Fine-Spun Cloth": "belt",
  "The Tal Rasha's Guardianship": "armor",
  "The Tal Rasha's Horadric Crest": "helm",
  "The Tal Rasha's Wrappings": "helm",
  "The Tancred's Battlegear": "helm",
  "The Tancred's Hobnails": "boots",
  "The Tancred's Skull": "helm",
  "The Tancred's Spine": "armor",
  "The Tancred's Weird": "amulet",
  "The Tannr Gorerod": "weapon",
  "The Tarnhelm": "helm",
  "The Tearhaunch": "boots",
  "The Telling of Beads": "amulet",
  "The Tempest": "weapon",
  "The Templar's Might": "armor",
  "The Third Eye": "amulet",
  "The Thundergod's Vigor": "belt",
  "The Tiamat's Rebuke": "offhand",
  "The Titan's Grip": "gloves",
  "The Todesfaelle Flamme": "weapon",
  "The Tomb Reaver": "weapon",
  "The Tombsong": "offhand",
  "The Toothrow": "armor",
  "The Torch of Iro": "weapon",
  "The Trang-Oul's Avatar": "offhand",
  "The Trang-Oul's Girth": "belt",
  "The Trang-Oul's Guise": "offhand",
  "The Treachery": "armor",
  "The Treads of Cthon": "boots",
  "The Twilight's Reflection": "offhand",
  "The Twitchthroe": "armor",
  "The Tyrael's Might": "armor",
  "The Uldyssian's Awakening": "weapon",
  "The Umbral Disk": "offhand",
  "The Ume's Lament": "weapon",
  "The Unbending Will": "weapon",
  "The Undead Crown": "helm",
  "The Ursa's Nightmare": "helm",
  "The Valkyrie Wing": "helm",
  "The Vampire Gaze": "helm",
  "The Veil of Steel": "helm",
  "The Venom": "weapon",
  "The Venom Grip": "gloves",
  "The Venom Ward": "armor",
  "The Verdungo's Hearty Cord": "belt",
  "The Vidala's Ambush": "armor",
  "The Vidala's Barb": "weapon",
  "The Vidala's Fetlock": "boots",
  "The Vidala's Rig": "armor",
  "The Vidala's Snare": "amulet",
  "The Vile Husk": "weapon",
  "The Viperfork": "weapon",
  "The Visceratuant": "offhand",
  "The Voice of Reason": "weapon",
  "The Wall of the Eyeless": "offhand",
  "The War Traveler": "boots",
  "The Ward": "offhand",
  "The Warlord's Trust": "weapon",
  "The Warpspear": "weapon",
  "The Warshrike": "weapon",
  "The Waterwalk": "boots",
  "The Wealth": "armor",
  "The Whispering Mirage": "weapon",
  "The White": "weapon",
  "The Whitstan's Guard": "offhand",
  "The Widowmaker": "weapon",
  "The Wildspeaker": "helm",
  "The Wilhelm's Pride": "belt",
  "The Wind": "weapon",
  "The Windforce": "weapon",
  "The Windhammer": "weapon",
  "The Wisdom": "helm",
  "The Wisp Projector": "ring",
  "The Witchwild String": "weapon",
  "The Witherstring": "weapon",
  "The Wizardspike": "weapon",
  "The Wizendraw": "weapon",
  "The Woestave": "weapon",
  "The Wolfhowl": "helm",
  "The Wormskull": "helm",
  "The Wraith Flight": "weapon",
  "The Wraithskin": "armor",
  "The Wrath": "weapon",
  "The Zakarum's Hand": "weapon",
  "The Zenith": "weapon",
  "The Zephyr": "weapon",
  "Third Eye": "amulet",
  "Throwing Spear": "weapon",
  "Thunder Maul": "weapon",
  "Thundergod's Vigor": "belt",
  "Thunderstroke": "weapon",
  "Tiamat's Rebuke": "offhand",
  "Tiara": "helm",
  "Titan's Grip": "gloves",
  "Todesfaelle Flamme": "weapon",
  "Tomb Reaver": "weapon",
  "Tombsong": "offhand",
  "Toothrow": "armor",
  "Torch of Iro": "weapon",
  "Trang-Oul's Avatar": "offhand",
  "Trang-Oul's Claws": "gloves",
  "Trang-Oul's Girth": "belt",
  "Trang-Oul's Guise": "helm",
  "Trang-Oul's Scales": "armor",
  "Trang-Oul's Wing": "offhand",
  "Treachery": "armor",
  "Treads of Cthon": "boots",
  "Trellised Armor": "armor",
  "Troll Belt": "belt",
  "Troll Nest": "offhand",
  "Twilight's Reflection": "offhand",
  "Twitchthroe": "armor",
  "Tyrael's Might": "armor",
  "Uldyssian's Awakening": "weapon",
  "Umbral Disk": "offhand",
  "Ume's Lament": "weapon",
  "Unbending Will": "weapon",
  "Undead Crown": "helm",
  "Unraveller Head": "offhand",
  "Ursa's Nightmare": "helm",
  "Valkyrie Wing": "helm",
  "Vambraces": "gloves",
  "Vampire Gaze": "helm",
  "Vampirebone Gloves": "gloves",
  "Veil of Steel": "helm",
  "Venom": "weapon",
  "Venom Grip": "gloves",
  "Venom Ward": "armor",
  "Venomous Amulet of Atlus": "amulet",
  "Venomous Amulet of Health": "amulet",
  "Venomous Amulet of Life": "amulet",
  "Venomous Amulet of Shock": "amulet",
  "Venomous Amulet of the Apprentice": "amulet",
  "Venomous Bone Wand of Hellfire": "weapon",
  "Venomous Diadem of Accuracy": "helm",
  "Verdungo's Hearty Cord": "belt",
  "Vidala's Ambush": "armor",
  "Vidala's Barb": "weapon",
  "Vidala's Fetlock": "boots",
  "Vidala's Rig": "armor",
  "Vidala's Snare": "amulet",
  "Vile Husk": "weapon",
  "Viperfork": "weapon",
  "Visceratuant": "offhand",
  "Voice of Reason": "weapon",
  "Volcanic Amulet of the Giant": "amulet",
  "Volcanic Amulet of the Whale": "amulet",
  "Wall of the Eyeless": "offhand",
  "War Bolts": "offhand",
  "War Boots": "boots",
  "War Fist": "weapon",
  "War Hat": "helm",
  "War Pike": "weapon",
  "War Traveler": "boots",
  "Ward": "offhand",
  "Warlord's Trust": "weapon",
  "Warpspear": "weapon",
  "Warshrike": "weapon",
  "Waterwalk": "boots",
  "Wealth": "armor",
  "Whispering Mirage": "weapon",
  "White": "weapon",
  "Whitstan's Guard": "offhand",
  "Widowmaker": "weapon",
  "Wildspeaker": "helm",
  "Wilhelm's Pride": "belt",
  "Wind": "weapon",
  "Windforce": "weapon",
  "Windhammer": "weapon",
  "Winged Axe": "weapon",
  "Winged Harpoon": "weapon",
  "Winged Knife": "weapon",
  "Wire Fleece": "armor",
  "Wisdom": "helm",
  "Wisp Projector": "ring",
  "Witch-hunter's Scissors Katar of Fast Repair": "weapon",
  "Witchwild String": "weapon",
  "Witherstring": "weapon",
  "Wizardspike": "weapon",
  "Wizendraw": "weapon",
  "Woestave": "weapon",
  "Wolfhowl": "helm",
  "Wormskull": "helm",
  "Wraith Flight": "weapon",
  "Wraithskin": "armor",
  "Wrath": "weapon",
  "Wyrmhide": "armor",
  "Wyrmhide Boots": "boots",
  "Yew Wand": "weapon",
  "Zakarum's Hand": "weapon",
  "Zenith": "weapon",
  "Zephyr": "weapon",
  "Zombie Head": "offhand"
}
